CHANGES.txt
LICENSE.txt
MANIFEST.in
README.txt
setup.py
src/p01/__init__.py
src/p01.securitypolicy.egg-info/PKG-INFO
src/p01.securitypolicy.egg-info/SOURCES.txt
src/p01.securitypolicy.egg-info/dependency_links.txt
src/p01.securitypolicy.egg-info/namespace_packages.txt
src/p01.securitypolicy.egg-info/not-zip-safe
src/p01.securitypolicy.egg-info/requires.txt
src/p01.securitypolicy.egg-info/top_level.txt
src/p01/securitypolicy/README.txt
src/p01/securitypolicy/__init__.py
src/p01/securitypolicy/configure.zcml
src/p01/securitypolicy/interfaces.py
src/p01/securitypolicy/securitypolicy.py
src/p01/securitypolicy/testing.py
src/p01/securitypolicy/tests.py