Metadata-Version: 1.0
Name: p01.securitypolicy
Version: 0.5.0
Summary: Annotation less securitypolicy implementation for Zope3
Home-page: http://pypi.python.org/pypi/p01.securitypolicy
Author: Roger Ineichen, Projekt01 GmbH
Author-email: dev@projekt01.ch
License: ZPL 2.1
Keywords: P01 securitypolicy components Zope3
Platform: UNKNOWN
Classifier: Development Status :: 4 - Beta
Classifier: Environment :: Web Environment
Classifier: Intended Audience :: Developers
Classifier: License :: OSI Approved :: Zope Public License
Classifier: Programming Language :: Python
Classifier: Natural Language :: English
Classifier: Operating System :: OS Independent
Classifier: Topic :: Internet :: WWW/HTTP
Classifier: Framework :: Zope3
